setup.py
functoolz/__init__.py
functoolz/core.py
functoolz.egg-info/PKG-INFO
functoolz.egg-info/SOURCES.txt
functoolz.egg-info/dependency_links.txt
functoolz.egg-info/not-zip-safe
functoolz.egg-info/top_level.txt