Metadata-Version: 1.0
Name: functoolz
Version: 0.4
Summary: More function tools
Home-page: http://github.com/mrocklin/functoolz/
Author: Matthew Rocklin
Author-email: mrocklin@gmail.com
License: BSD
Platform: UNKNOWN
